MANIFEST.in
README.md
setup.py
volatility_profile_builder/Colorer.py
volatility_profile_builder/__init__.py
volatility_profile_builder/centos.py
volatility_profile_builder/debian.py
volatility_profile_builder/fedora.py
volatility_profile_builder/helpers.py
volatility_profile_builder/ubuntu.py
volatility_profile_builder/volatility_profile_builder.py
volatility_profile_builder.egg-info/PKG-INFO
volatility_profile_builder.egg-info/SOURCES.txt
volatility_profile_builder.egg-info/dependency_links.txt
volatility_profile_builder.egg-info/entry_points.txt
volatility_profile_builder.egg-info/requires.txt
volatility_profile_builder.egg-info/top_level.txt
volatility_profile_builder/docker/Dockerfile_alpine
volatility_profile_builder/docker/Dockerfile_centos
volatility_profile_builder/docker/Dockerfile_debian
volatility_profile_builder/docker/Dockerfile_fedora
volatility_profile_builder/docker/Dockerfile_ubuntu